riitag/.DS_Store
riitag/__init__.py
riitag/py.typed
riitag/riitag.py
riitag/types.py
riitag_sdk-0.1.0.dist-info/METADATA
riitag_sdk-0.1.0.dist-info/WHEEL
riitag_sdk-0.1.0.dist-info/licenses/LICENSE.md
riitag_sdk-0.1.0.dist-info/RECORD
