Metadata-Version: 2.1
Name: riitag-sdk
Version: 0.1.0
Summary: RiiTag Python SDK
Project-URL: Source Code, https://github.com/owenvoke/riitag-python-sdk
Project-URL: Issues, https://github.com/owenvoke/riitag-python-sdk/issues
Author-email: Owen Voke <development@voke.dev>
License-Expression: MIT
License-File: LICENSE.md
Keywords: riitag,sdk
Classifier: Intended Audience :: Developers
Classifier: License :: OSI Approved :: MIT License
Classifier: Programming Language :: Python :: 3 :: Only
Requires-Python: >=3.11.0
Requires-Dist: requests>=2.28.1
